CHANGES.txt
DEPENDENCES.txt
README.txt
setup.py
src/ng/__init__.py
src/ng.app.rubricator.tag.egg-info/PKG-INFO
src/ng.app.rubricator.tag.egg-info/SOURCES.txt
src/ng.app.rubricator.tag.egg-info/dependency_links.txt
src/ng.app.rubricator.tag.egg-info/namespace_packages.txt
src/ng.app.rubricator.tag.egg-info/not-zip-safe
src/ng.app.rubricator.tag.egg-info/requires.txt
src/ng.app.rubricator.tag.egg-info/top_level.txt
src/ng/app/__init__.py
src/ng/app/rubricator/__init__.py
src/ng/app/rubricator/tag/__init__.py
src/ng/app/rubricator/tag/configure.zcml
src/ng/app/rubricator/tag/ng.app.rubricator.tag.txt
src/ng/app/rubricator/tag/etc/ng.app.rubricator.tag-configure.zcml
src/ng/app/rubricator/tag/tagitemannotation/__init__.py
src/ng/app/rubricator/tag/tagitemannotation/configure.zcml
src/ng/app/rubricator/tag/tagitemannotation/interfaces.py
src/ng/app/rubricator/tag/tagitemannotation/tagitemannotation.py
src/ng/app/rubricator/tag/tagitemannotation/tagitemannotationableadapter.py
src/ng/app/rubricator/tag/tagitemannotation/browser/__init__.py
src/ng/app/rubricator/tag/tagitemannotation/browser/configure.zcml
src/ng/app/rubricator/tag/tagrubricannotation/__init__.py
src/ng/app/rubricator/tag/tagrubricannotation/configure.zcml
src/ng/app/rubricator/tag/tagrubricannotation/interfaces.py
src/ng/app/rubricator/tag/tagrubricannotation/tagrubricannotation.py
src/ng/app/rubricator/tag/tagrubricannotation/tagrubricannotationableadapter.py
src/ng/app/rubricator/tag/tagrubricannotation/tagrubricsearchadapter.py
src/ng/app/rubricator/tag/tagrubricannotation/browser/__init__.py
src/ng/app/rubricator/tag/tagrubricannotation/browser/configure.zcml
src/ng/app/rubricator/tag/tagvocabulary/__init__.py
src/ng/app/rubricator/tag/tagvocabulary/tagvocabulary.py
